mopidy_nuvo/__init__.py
mopidy_nuvo/connect.py
mopidy_nuvo/ext.conf
mopidy_nuvo/frontend.py
mopidy_nuvo/interface.py
Mopidy_Nuvo-0.2.0.dist-info/LICENSE
Mopidy_Nuvo-0.2.0.dist-info/METADATA
Mopidy_Nuvo-0.2.0.dist-info/WHEEL
Mopidy_Nuvo-0.2.0.dist-info/entry_points.txt
Mopidy_Nuvo-0.2.0.dist-info/top_level.txt
Mopidy_Nuvo-0.2.0.dist-info/RECORD
