Metadata-Version: 2.1
Name: Mopidy-Nuvo
Version: 0.2.0
Summary: Mopidy extension for using Nuvo control pads as a Mopidy frontend.
Home-page: https://github.com/legusx/mopidy-nuvo
Author: Logan Henrie
Author-email: legusx@legusx.dev
License: Apache License, Version 2.0
Platform: UNKNOWN
Classifier: Intended Audience :: End Users/Desktop
Classifier: License :: OSI Approved :: Apache Software License
Classifier: Operating System :: OS Independent
Classifier: Programming Language :: Python :: 3
Classifier: Topic :: Multimedia :: Sound/Audio :: Players
License-File: LICENSE
Requires-Dist: setuptools
Requires-Dist: Mopidy (>=0.14)
Requires-Dist: Pykka (>=1.1)
Requires-Dist: pyserial
